{
  "project_info": {
    "project_number": "928318478685",
    "firebase_url": "https://evedb-98c72.firebaseio.com",
    "project_id": "evedb-98c72",
    "storage_bucket": "evedb-98c72.appspot.com"
  },
  "client": [
    {
      "client_info": {
        "mobilesdk_app_id": "1:928318478685:android:aed7e86ca1e7457e",
        "android_client_info": {
          "package_name": "com.example.javier_t.eventuallytest"
        }
      },
      "oauth_client": [
        {
          "client_id": "928318478685-r3capi7c60mhm6k8lv349r4vtvgmuat2.apps.googleusercontent.com",
          "client_type": 1,
          "android_info": {
            "package_name": "com.example.javier_t.eventuallytest",
            "certificate_hash": "6387e32119778cd5574bfc13ee2e976515e98aee"
          }
        },
        {
          "client_id": "928318478685-i71qpsd5ncd96st03varlf7muj0oin3h.apps.googleusercontent.com",
          "client_type": 3
        }
      ],
      "api_key": [
        {
          "current_key": "AIzaSyDA9jQlREq9bUrTsghXVNqaOvZPg-i9_Pc"
        }
      ],
      "services": {
        "analytics_service": {
          "status": 1
        },
        "appinvite_service": {
          "status": 2,
          "other_platform_oauth_client": [
            {
              "client_id": "928318478685-i71qpsd5ncd96st03varlf7muj0oin3h.apps.googleusercontent.com",
              "client_type": 3
            }
          ]
        },
        "ads_service": {
          "status": 2
        }
      }
    }
  ],
  "configuration_version": "1"
}